locality_splitting/__init__.py
locality_splitting/block_equivalency_file.py
locality_splitting/metrics.py
locality_splitting-0.2.1.dist-info/LICENSE.txt
locality_splitting-0.2.1.dist-info/METADATA
locality_splitting-0.2.1.dist-info/WHEEL
locality_splitting-0.2.1.dist-info/top_level.txt
locality_splitting-0.2.1.dist-info/RECORD
