Metadata-Version: 2.1
Name: locality-splitting
Version: 0.2.1
Summary: Implementation of locality splitting metrics for political redistricing plans
Home-page: https://github.com/jacobwachspress/locality-splitting
Author: Jacob Wachspress
Author-email: jacobwachspress@gmail.com
License: UNKNOWN
Platform: UNKNOWN
Classifier: Programming Language :: Python :: 3
Classifier: License :: OSI Approved :: MIT License
Classifier: Operating System :: OS Independent
Requires-Python: >=3
License-File: LICENSE.txt
